MANIFEST.in
relately-server
setup.cfg
setup.py
relately/__init__.py
relately/engine.py
relately/select.py
relately/server.py
relately.egg-info/PKG-INFO
relately.egg-info/SOURCES.txt
relately.egg-info/dependency_links.txt
relately.egg-info/not-zip-safe
relately.egg-info/pbr.json
relately.egg-info/requires.txt
relately.egg-info/top_level.txt
relately/templates/select.sql
relately/templates/select_outer.sql
relately/templates/sys/sql_error.txt
test/__init__.py
test/test_engine.py
test/test_query.py
test/test_server.py