Metadata-Version: 1.1
Name: relately
Version: 0.0.5
Summary: PostgreSQL REST access
Home-page: http://github.com/cacahootie/relately/
Author: Bradley Alan Smith
Author-email: brad.alan.smith@gmail.com
License: MIT
Platform: any
Classifier: Development Status :: 1 - Planning
Classifier: Environment :: Web Environment
Classifier: Framework :: Flask
Classifier: Intended Audience :: Developers
Classifier: License :: OSI Approved :: MIT License
Classifier: Operating System :: OS Independent
Classifier: Programming Language :: Python
Classifier: Programming Language :: Python :: 2.7
Classifier: Topic :: Internet :: WWW/HTTP :: Dynamic Content
Classifier: Topic :: Software Development :: Libraries :: Python Modules
